{
    "BaseModel.bf874afc-6155-401f-afaa-050c27cb8fe2": {
        "id": "bf874afc-6155-401f-afaa-050c27cb8fe2",
        "created_at": "2023-12-05T23:54:29.574583",
        "updated_at": "2023-12-05T23:54:29.574599",
        "name": "My_First_Model",
        "my_number": 89,
        "__class__": "BaseModel"
    },
    "Amenity.6d9ba9a3-e1d2-4c8d-9e24-ee4cd5750684": {
        "id": "6d9ba9a3-e1d2-4c8d-9e24-ee4cd5750684",
        "created_at": "2023-12-05T23:54:29.576568",
        "updated_at": "2023-12-05T23:54:29.576570",
        "__class__": "Amenity"
    },
    "Amenity.369b6761-a7e7-44c9-bb98-eeb703940da0": {
        "id": "369b6761-a7e7-44c9-bb98-eeb703940da0",
        "created_at": "2023-12-05T23:54:29.576627",
        "updated_at": "2023-12-05T23:54:29.576627",
        "__class__": "Amenity"
    },
    "Amenity.2c4c453a-8403-4f15-a4f2-9a4f3e38a715": {
        "id": "2c4c453a-8403-4f15-a4f2-9a4f3e38a715",
        "created_at": "2023-12-05T23:54:29.576663",
        "updated_at": "2023-12-05T23:54:29.576664",
        "__class__": "Amenity"
    },
    "Amenity.a6fe264f-2c0f-4686-9c5f-b3199c0e6a99": {
        "id": "a6fe264f-2c0f-4686-9c5f-b3199c0e6a99",
        "created_at": "2023-12-05T23:54:29.576691",
        "updated_at": "2023-12-05T23:54:29.576692",
        "__class__": "Amenity"
    },
    "Amenity.0f16ce91-46b2-434f-8ea1-97b90c54da74": {
        "id": "0f16ce91-46b2-434f-8ea1-97b90c54da74",
        "created_at": "2023-12-05T23:54:29.576719",
        "updated_at": "2023-12-05T23:54:29.576719",
        "__class__": "Amenity"
    },
    "Amenity.e957f3c6-7f1f-43a3-8901-9d4fe831d072": {
        "id": "e957f3c6-7f1f-43a3-8901-9d4fe831d072",
        "created_at": "2023-12-05T23:54:29.576743",
        "updated_at": "2023-12-05T23:54:29.576747",
        "__class__": "Amenity"
    },
    "Amenity.4768697a-6ef2-49d4-a03d-31af967dc4d7": {
        "id": "4768697a-6ef2-49d4-a03d-31af967dc4d7",
        "created_at": "2023-12-05T23:54:29.576906",
        "updated_at": "2023-12-05T23:54:29.576911",
        "__class__": "Amenity"
    },
    "Amenity.113221a7-6501-47eb-9ccc-61ea65c11ba2": {
        "id": "123456",
        "created_at": "2023-12-05T23:54:29.577211",
        "updated_at": "2023-12-05T23:54:29.577212",
        "__class__": "Amenity"
    },
    "Amenity.a31462e5-57ca-4de1-88f2-52a94efc9a0b": {
        "id": "123456",
        "created_at": "2023-12-05T23:54:29.577246",
        "updated_at": "2023-12-05T23:54:29.577247",
        "name": "Amenity Name",
        "__class__": "Amenity"
    },
    "Amenity.feb26318-1f02-492c-ab65-5b23b8525d57": {
        "id": "123456",
        "created_at": "2023-12-05T23:54:29.577313",
        "updated_at": "2023-12-05T23:54:29.577314",
        "__class__": "Amenity"
    },
    "Amenity.c1aaa414-cb9a-4eab-97d1-93591bba6753": {
        "id": "123456",
        "created_at": "2023-12-05T23:54:29.577416",
        "updated_at": "2023-12-05T23:54:29.577417",
        "name": "Amenity Name",
        "__class__": "Amenity"
    },
    "BaseModel.0b5aa79c-c450-4181-b1f3-0cb1b7712284": {
        "id": "0b5aa79c-c450-4181-b1f3-0cb1b7712284",
        "created_at": "2023-12-05T23:54:29.577475",
        "updated_at": "2023-12-05T23:54:29.577475",
        "__class__": "BaseModel"
    },
    "BaseModel.c01c8289-3ccf-47dc-b932-cc10e2fdf0be": {
        "id": "c01c8289-3ccf-47dc-b932-cc10e2fdf0be",
        "created_at": "2023-12-05T23:54:29.577502",
        "updated_at": "2023-12-05T23:54:29.577504",
        "__class__": "BaseModel"
    },
    "BaseModel.c05659ad-f9f8-4da8-b67c-c4356d76fca7": {
        "id": "c05659ad-f9f8-4da8-b67c-c4356d76fca7",
        "created_at": "2023-12-05T23:54:29.577528",
        "updated_at": "2023-12-05T23:54:29.577529",
        "__class__": "BaseModel"
    },
    "BaseModel.24b244e7-3e81-4a64-8a0a-27136cd1e3e7": {
        "id": "24b244e7-3e81-4a64-8a0a-27136cd1e3e7",
        "created_at": "2023-12-05T23:54:29.577555",
        "updated_at": "2023-12-05T23:54:29.577557",
        "__class__": "BaseModel"
    },
    "BaseModel.5138254c-16a1-40ac-ae75-0f98f1d82192": {
        "id": "5138254c-16a1-40ac-ae75-0f98f1d82192",
        "created_at": "2023-12-05T23:54:29.577590",
        "updated_at": "2023-12-05T23:54:29.577591",
        "__class__": "BaseModel"
    },
    "BaseModel.d94a6026-4a13-41dc-9d08-c77f2950efed": {
        "id": "123456",
        "created_at": "2023-12-05T23:54:29.577613",
        "updated_at": "2023-12-05T23:54:29.577613",
        "__class__": "BaseModel"
    },
    "BaseModel.0273b967-5ee1-42b0-b2d6-95577cea8696": {
        "id": "0273b967-5ee1-42b0-b2d6-95577cea8696",
        "created_at": "2023-12-05T23:54:29.577649",
        "updated_at": "2023-12-05T23:54:29.577649",
        "__class__": "BaseModel"
    },
    "BaseModel.4006d514-fbc2-4271-9b98-e00f5876608c": {
        "id": "4006d514-fbc2-4271-9b98-e00f5876608c",
        "created_at": "2023-12-05T23:54:29.667096",
        "updated_at": "2023-12-05T23:54:29.667103",
        "__class__": "BaseModel"
    },
    "BaseModel.8e359f0f-642f-41e6-b810-1fd1c203a5d5": {
        "id": "8e359f0f-642f-41e6-b810-1fd1c203a5d5",
        "created_at": "2023-12-05T23:54:29.667457",
        "updated_at": "2023-12-05T23:54:29.667460",
        "__class__": "BaseModel"
    },
    "BaseModel.5349bc50-896c-4606-bab1-d36953bf794a": {
        "id": "5349bc50-896c-4606-bab1-d36953bf794a",
        "created_at": "2023-12-05T23:54:29.747884",
        "updated_at": "2023-12-05T23:54:29.747889",
        "__class__": "BaseModel"
    },
    "BaseModel.b92e0a07-d949-4b82-9588-c74cb1ccc096": {
        "id": "b92e0a07-d949-4b82-9588-c74cb1ccc096",
        "created_at": "2023-12-05T23:54:29.748017",
        "updated_at": "2023-12-05T23:54:29.748017",
        "__class__": "BaseModel"
    },
    "BaseModel.3b5b5261-a6ed-442c-80a6-1a30eba5d857": {
        "id": "3b5b5261-a6ed-442c-80a6-1a30eba5d857",
        "created_at": "2023-12-05T23:54:29.748024",
        "updated_at": "2023-12-05T23:54:29.748024",
        "__class__": "BaseModel"
    },
    "BaseModel.15466618-0ba1-48d1-aab1-d84a91d7f794": {
        "id": "15466618-0ba1-48d1-aab1-d84a91d7f794",
        "created_at": "2023-12-05T23:54:29.748050",
        "updated_at": "2023-12-05T23:54:29.748050",
        "__class__": "BaseModel"
    },
    "BaseModel.5359fb43-74df-42c8-98d4-346441743c1e": {
        "id": "5359fb43-74df-42c8-98d4-346441743c1e",
        "created_at": "2023-12-05T23:54:29.748136",
        "updated_at": "2023-12-05T23:54:29.877144",
        "__class__": "BaseModel"
    },
    "BaseModel.68b19224-62a5-4475-bd40-7207e789e6d0": {
        "id": "68b19224-62a5-4475-bd40-7207e789e6d0",
        "created_at": "2023-12-05T23:54:29.878600",
        "updated_at": "2023-12-05T23:54:29.878625",
        "__class__": "BaseModel"
    },
    "BaseModel.7ad2a516-4674-4b37-8551-6e0a699f7ef6": {
        "id": "7ad2a516-4674-4b37-8551-6e0a699f7ef6",
        "created_at": "2023-12-05T23:54:29.879527",
        "updated_at": "2023-12-05T23:54:29.879530",
        "__class__": "BaseModel"
    },
    "BaseModel.84413871-3019-4a35-9a47-cc8e27c3d404": {
        "id": "84413871-3019-4a35-9a47-cc8e27c3d404",
        "created_at": "2023-12-05T23:54:29.879803",
        "updated_at": "2023-12-05T23:54:30.283298",
        "__class__": "BaseModel"
    },
    "BaseModel.32c71181-8a22-4082-b3ca-0104200790e9": {
        "id": "32c71181-8a22-4082-b3ca-0104200790e9",
        "created_at": "2023-12-05T23:54:30.285275",
        "updated_at": "2023-12-05T23:54:30.285280",
        "__class__": "BaseModel"
    },
    "BaseModel.90a2d123-d1f9-47b5-a5bf-62515297489f": {
        "id": "90a2d123-d1f9-47b5-a5bf-62515297489f",
        "created_at": "2023-12-05T23:54:30.285531",
        "updated_at": "2023-12-05T23:54:30.285534",
        "name": "Holberton",
        "my_number": 98,
        "__class__": "BaseModel"
    },
    "BaseModel.95f13217-c036-449f-965a-03f6a54cb712": {
        "id": "95f13217-c036-449f-965a-03f6a54cb712",
        "created_at": "2023-12-05T23:54:30.285657",
        "updated_at": "2023-12-05T23:54:30.285658",
        "__class__": "BaseModel"
    },
    "BaseModel.1d23e8c5-da7a-421b-8e41-202d9e4ebe04": {
        "id": "1d23e8c5-da7a-421b-8e41-202d9e4ebe04",
        "created_at": "2023-12-05T23:54:30.285830",
        "updated_at": "2023-12-05T23:54:30.285832",
        "__class__": "BaseModel"
    },
    "BaseModel.a01b84a1-76aa-4da3-9545-ca47121f7d27": {
        "id": "123456",
        "created_at": "2023-12-05T23:54:30.285936",
        "updated_at": "2023-12-05T23:54:30.285936",
        "__class__": "BaseModel"
    },
    "BaseModel.b20fd4d9-d249-4655-9203-d946208016d7": {
        "id": "b20fd4d9-d249-4655-9203-d946208016d7",
        "created_at": "2023-12-05T23:54:30.286075",
        "updated_at": "2023-12-05T23:54:30.286076",
        "__class__": "BaseModel"
    },
    "BaseModel.8a1fbb73-c488-481f-8ad8-5753ac03121b": {
        "id": "8a1fbb73-c488-481f-8ad8-5753ac03121b",
        "created_at": "2023-12-05T23:54:30.286171",
        "updated_at": "2023-12-05T23:54:30.286172",
        "__class__": "BaseModel"
    },
    "City.9a1fbbaa-1de8-48bd-b453-cc3e22c6c022": {
        "id": "9a1fbbaa-1de8-48bd-b453-cc3e22c6c022",
        "created_at": "2023-12-05T23:54:30.286375",
        "updated_at": "2023-12-05T23:54:30.286377",
        "__class__": "City"
    },
    "City.5498eabc-1600-4908-8f73-57153b59a062": {
        "id": "5498eabc-1600-4908-8f73-57153b59a062",
        "created_at": "2023-12-05T23:54:30.286496",
        "updated_at": "2023-12-05T23:54:30.286497",
        "__class__": "City"
    },
    "City.0316ecac-0f02-48dc-8f13-98228da7ba50": {
        "id": "0316ecac-0f02-48dc-8f13-98228da7ba50",
        "created_at": "2023-12-05T23:54:30.286594",
        "updated_at": "2023-12-05T23:54:30.286595",
        "__class__": "City"
    },
    "City.058286b7-c1db-4b9f-ac16-1b709535b1e2": {
        "id": "058286b7-c1db-4b9f-ac16-1b709535b1e2",
        "created_at": "2023-12-05T23:54:30.286762",
        "updated_at": "2023-12-05T23:54:30.286768",
        "__class__": "City"
    },
    "City.01c4ec5f-cc76-499a-a796-2810234b0154": {
        "id": "01c4ec5f-cc76-499a-a796-2810234b0154",
        "created_at": "2023-12-05T23:54:30.287069",
        "updated_at": "2023-12-05T23:54:30.287072",
        "__class__": "City"
    },
    "City.e5307bb1-908a-49a0-be6b-2ad4518bc5be": {
        "id": "e5307bb1-908a-49a0-be6b-2ad4518bc5be",
        "created_at": "2023-12-05T23:54:30.287320",
        "updated_at": "2023-12-05T23:54:30.287323",
        "__class__": "City"
    },
    "City.f70fae9f-072e-4013-a7b0-b563d93ca09e": {
        "id": "123456",
        "created_at": "2023-12-05T23:54:30.287502",
        "updated_at": "2023-12-05T23:54:30.287504",
        "state_id": "state_1",
        "__class__": "City"
    },
    "City.ef7dcb61-3cde-4ddd-a896-bd997cdfd7e7": {
        "id": "123456",
        "created_at": "2023-12-05T23:54:30.287710",
        "updated_at": "2023-12-05T23:54:30.287712",
        "state_id": "state_1",
        "name": "City Name",
        "__class__": "City"
    },
    "City.3827a75b-e3c3-4c6b-8164-0753d9edec01": {
        "id": "123456",
        "created_at": "2023-12-05T23:54:30.287885",
        "updated_at": "2023-12-05T23:54:30.287888",
        "state_id": "state_1",
        "__class__": "City"
    },
    "City.20d23697-f31e-4b0a-88ad-7a316a0dff05": {
        "id": "123456",
        "created_at": "2023-12-05T23:54:30.288064",
        "updated_at": "2023-12-05T23:54:30.288066",
        "state_id": "state_1",
        "name": "City Name",
        "__class__": "City"
    },
    "Place.fad93bd5-3671-4bac-b33b-890a3260a503": {
        "id": "fad93bd5-3671-4bac-b33b-890a3260a503",
        "created_at": "2023-12-05T23:54:30.288337",
        "updated_at": "2023-12-05T23:54:30.288340",
        "__class__": "Place"
    },
    "Place.fec290b4-b060-4090-be64-8f3fc00a5b17": {
        "id": "fec290b4-b060-4090-be64-8f3fc00a5b17",
        "created_at": "2023-12-05T23:54:30.288522",
        "updated_at": "2023-12-05T23:54:30.288525",
        "__class__": "Place"
    },
    "Place.aef07be1-64fc-4ab9-a6e3-1fcec8d14ea1": {
        "id": "aef07be1-64fc-4ab9-a6e3-1fcec8d14ea1",
        "created_at": "2023-12-05T23:54:30.288676",
        "updated_at": "2023-12-05T23:54:30.288679",
        "__class__": "Place"
    },
    "Place.eb3b5812-f6a2-4b5e-9f27-43e702039b77": {
        "id": "eb3b5812-f6a2-4b5e-9f27-43e702039b77",
        "created_at": "2023-12-05T23:54:30.288821",
        "updated_at": "2023-12-05T23:54:30.288823",
        "__class__": "Place"
    },
    "Place.01d36af3-e3dc-48dc-b608-3ad3c02181b8": {
        "id": "01d36af3-e3dc-48dc-b608-3ad3c02181b8",
        "created_at": "2023-12-05T23:54:30.288984",
        "updated_at": "2023-12-05T23:54:30.288986",
        "__class__": "Place"
    },
    "Place.3aa596fd-8ee7-46f8-8c1a-b5ed0abdbfe0": {
        "id": "3aa596fd-8ee7-46f8-8c1a-b5ed0abdbfe0",
        "created_at": "2023-12-05T23:54:30.289122",
        "updated_at": "2023-12-05T23:54:30.289124",
        "__class__": "Place"
    },
    "Place.41927dd4-8bf3-433d-81fa-b5c28d4b3dab": {
        "id": "41927dd4-8bf3-433d-81fa-b5c28d4b3dab",
        "created_at": "2023-12-05T23:54:30.289293",
        "updated_at": "2023-12-05T23:54:30.289295",
        "__class__": "Place"
    },
    "Place.98220552-79b8-45ba-9167-75399122cde7": {
        "id": "98220552-79b8-45ba-9167-75399122cde7",
        "created_at": "2023-12-05T23:54:30.289508",
        "updated_at": "2023-12-05T23:54:30.289511",
        "__class__": "Place"
    },
    "Place.aa65affe-7f7f-4d8f-b0d5-fa816770ff85": {
        "id": "aa65affe-7f7f-4d8f-b0d5-fa816770ff85",
        "created_at": "2023-12-05T23:54:30.289699",
        "updated_at": "2023-12-05T23:54:30.289701",
        "__class__": "Place"
    },
    "Place.99eb0415-1ac2-46e3-ba4b-4126bb087bf0": {
        "id": "99eb0415-1ac2-46e3-ba4b-4126bb087bf0",
        "created_at": "2023-12-05T23:54:30.289840",
        "updated_at": "2023-12-05T23:54:30.289843",
        "__class__": "Place"
    },
    "Place.8d793526-c76b-4c36-b36c-0fef477def1f": {
        "id": "8d793526-c76b-4c36-b36c-0fef477def1f",
        "created_at": "2023-12-05T23:54:30.289989",
        "updated_at": "2023-12-05T23:54:30.289992",
        "__class__": "Place"
    },
    "Place.fb79437f-fa6b-4593-80fa-5cab821b3d37": {
        "id": "fb79437f-fa6b-4593-80fa-5cab821b3d37",
        "created_at": "2023-12-05T23:54:30.290129",
        "updated_at": "2023-12-05T23:54:30.290131",
        "__class__": "Place"
    },
    "Place.f2510e17-a3ac-444c-aeef-710332f7990c": {
        "id": "f2510e17-a3ac-444c-aeef-710332f7990c",
        "created_at": "2023-12-05T23:54:30.290268",
        "updated_at": "2023-12-05T23:54:30.290271",
        "__class__": "Place"
    },
    "Place.af6a991f-2d6b-4aed-963a-f42271f3e278": {
        "id": "af6a991f-2d6b-4aed-963a-f42271f3e278",
        "created_at": "2023-12-05T23:54:30.290424",
        "updated_at": "2023-12-05T23:54:30.290445",
        "__class__": "Place"
    },
    "Place.027efe29-ef41-46b2-9641-8cc1668430a3": {
        "id": "027efe29-ef41-46b2-9641-8cc1668430a3",
        "created_at": "2023-12-05T23:54:30.292115",
        "updated_at": "2023-12-05T23:54:30.292139",
        "__class__": "Place"
    },
    "Place.2eb371ea-b192-49f4-9ca9-562f8c7bb2cb": {
        "id": "123456",
        "created_at": "2023-12-05T23:54:30.292649",
        "updated_at": "2023-12-05T23:54:30.292650",
        "city_id": "789",
        "user_id": "101112",
        "__class__": "Place"
    },
    "Place.151438b0-0f1d-4985-a4d0-7f32e7bad1e5": {
        "id": "123456",
        "created_at": "2023-12-05T23:54:30.292741",
        "updated_at": "2023-12-05T23:54:30.292742",
        "city_id": "789",
        "user_id": "101112",
        "name": "Place Name",
        "__class__": "Place"
    },
    "Place.6108b835-fd16-4910-9ff4-4ccee371bc07": {
        "id": "123456",
        "created_at": "2023-12-05T23:54:30.292788",
        "updated_at": "2023-12-05T23:54:30.292789",
        "city_id": "789",
        "user_id": "101112",
        "__class__": "Place"
    },
    "Place.80cd4cb4-63a0-43f8-a6cc-c2f8b81871b4": {
        "id": "123456",
        "created_at": "2023-12-05T23:54:30.292838",
        "updated_at": "2023-12-05T23:54:30.292840",
        "city_id": "789",
        "user_id": "101112",
        "name": "Place Name",
        "__class__": "Place"
    },
    "Place.851c4026-ce91-4c0a-80fb-840e367d6f04": {
        "id": "851c4026-ce91-4c0a-80fb-840e367d6f04",
        "created_at": "2023-12-05T23:54:30.292906",
        "updated_at": "2023-12-05T23:54:30.292907",
        "__class__": "Place"
    },
    "Review.58d749bd-cae3-490d-a9ce-e8985f767eab": {
        "id": "58d749bd-cae3-490d-a9ce-e8985f767eab",
        "created_at": "2023-12-05T23:54:30.292991",
        "updated_at": "2023-12-05T23:54:30.292992",
        "__class__": "Review"
    },
    "Review.e8319c2b-2061-4c69-b355-83db576495bc": {
        "id": "e8319c2b-2061-4c69-b355-83db576495bc",
        "created_at": "2023-12-05T23:54:30.293034",
        "updated_at": "2023-12-05T23:54:30.293035",
        "__class__": "Review"
    },
    "Review.1ebc6227-3819-433f-9287-83c9487c0a56": {
        "id": "1ebc6227-3819-433f-9287-83c9487c0a56",
        "created_at": "2023-12-05T23:54:30.293084",
        "updated_at": "2023-12-05T23:54:30.293085",
        "__class__": "Review"
    },
    "Review.5afdf365-7cd4-423d-b082-b4a9772870fc": {
        "id": "5afdf365-7cd4-423d-b082-b4a9772870fc",
        "created_at": "2023-12-05T23:54:30.293123",
        "updated_at": "2023-12-05T23:54:30.293124",
        "__class__": "Review"
    },
    "Review.57276d3d-2bdb-44dd-89e2-7a9edbc35dde": {
        "id": "57276d3d-2bdb-44dd-89e2-7a9edbc35dde",
        "created_at": "2023-12-05T23:54:30.293160",
        "updated_at": "2023-12-05T23:54:30.293160",
        "__class__": "Review"
    },
    "Review.268ff0ae-bce8-44b0-b3d4-651037785dfb": {
        "id": "268ff0ae-bce8-44b0-b3d4-651037785dfb",
        "created_at": "2023-12-05T23:54:30.293195",
        "updated_at": "2023-12-05T23:54:30.293200",
        "__class__": "Review"
    },
    "Review.89008446-cec3-4a54-8688-8d420fecf1c0": {
        "id": "89008446-cec3-4a54-8688-8d420fecf1c0",
        "created_at": "2023-12-05T23:54:30.293890",
        "updated_at": "2023-12-05T23:54:30.293899",
        "__class__": "Review"
    },
    "Review.83069db2-3aa4-4615-83eb-f20ca4c3d947": {
        "id": "123456",
        "created_at": "2023-12-05T23:54:30.294513",
        "updated_at": "2023-12-05T23:54:30.294514",
        "place_id": "789",
        "user_id": "101112",
        "__class__": "Review"
    },
    "Review.1e345ee4-0142-4e7d-86c5-bb3f294d6922": {
        "id": "123456",
        "created_at": "2023-12-05T23:54:30.294568",
        "updated_at": "2023-12-05T23:54:30.294569",
        "place_id": "789",
        "user_id": "101112",
        "text": "Review Text",
        "__class__": "Review"
    },
    "Review.d3602460-4c2a-4f91-9986-36573a3853ad": {
        "id": "d3602460-4c2a-4f91-9986-36573a3853ad",
        "created_at": "2023-12-05T23:54:30.294631",
        "updated_at": "2023-12-05T23:54:30.294632",
        "__class__": "Review"
    },
    "Review.8bc25f20-4ad1-4994-a7f8-dc459c844c08": {
        "id": "123456",
        "created_at": "2023-12-05T23:54:30.294670",
        "updated_at": "2023-12-05T23:54:30.294671",
        "place_id": "789",
        "user_id": "101112",
        "__class__": "Review"
    },
    "Review.3801e611-34cf-444d-af23-6d0b5e62de1e": {
        "id": "123456",
        "created_at": "2023-12-05T23:54:30.294722",
        "updated_at": "2023-12-05T23:54:30.294722",
        "place_id": "789",
        "user_id": "101112",
        "text": "Review Text",
        "__class__": "Review"
    },
    "Review.fb67e64f-29fe-4196-ada9-59b18cb972c8": {
        "id": "fb67e64f-29fe-4196-ada9-59b18cb972c8",
        "created_at": "2023-12-05T23:54:30.294794",
        "updated_at": "2023-12-05T23:54:30.294795",
        "__class__": "Review"
    },
    "State.2c905ce3-217d-49db-a33a-a2f218fa9e01": {
        "id": "2c905ce3-217d-49db-a33a-a2f218fa9e01",
        "created_at": "2023-12-05T23:54:30.294873",
        "updated_at": "2023-12-05T23:54:30.294874",
        "__class__": "State"
    },
    "State.dd2a94ab-fe35-4b30-971c-e478ed92c722": {
        "id": "dd2a94ab-fe35-4b30-971c-e478ed92c722",
        "created_at": "2023-12-05T23:54:30.294920",
        "updated_at": "2023-12-05T23:54:30.294920",
        "__class__": "State"
    },
    "State.90385db1-57fc-4931-b9db-09f2d66f595b": {
        "id": "90385db1-57fc-4931-b9db-09f2d66f595b",
        "created_at": "2023-12-05T23:54:30.294970",
        "updated_at": "2023-12-05T23:54:30.294971",
        "__class__": "State"
    },
    "State.53a03057-6858-4be5-9c15-f0762588f9bb": {
        "id": "53a03057-6858-4be5-9c15-f0762588f9bb",
        "created_at": "2023-12-05T23:54:30.295015",
        "updated_at": "2023-12-05T23:54:30.295015",
        "__class__": "State"
    },
    "State.4e18bea2-0ae4-47b2-895a-a9fba62d6b04": {
        "id": "4e18bea2-0ae4-47b2-895a-a9fba62d6b04",
        "created_at": "2023-12-05T23:54:30.295064",
        "updated_at": "2023-12-05T23:54:30.295065",
        "__class__": "State"
    },
    "State.7da30b87-b4ea-4b3b-8a2b-ce416dff2f77": {
        "id": "7da30b87-b4ea-4b3b-8a2b-ce416dff2f77",
        "created_at": "2023-12-05T23:54:30.295113",
        "updated_at": "2023-12-05T23:54:30.295119",
        "__class__": "State"
    },
    "State.0fdc701f-3590-470b-bca0-2778f33dd6b7": {
        "id": "0fdc701f-3590-470b-bca0-2778f33dd6b7",
        "created_at": "2023-12-05T23:54:30.295823",
        "updated_at": "2023-12-05T23:54:30.295833",
        "__class__": "State"
    }
}